litrl/__init__.py
litrl/__main__.py
litrl/_version.py
litrl/py.typed
litrl/train.py
litrl/algo/__init__.py
litrl/algo/mcts/__init__.py
litrl/algo/mcts/agent.py
litrl/algo/mcts/backpropagate.py
litrl/algo/mcts/edge.py
litrl/algo/mcts/expansion.py
litrl/algo/mcts/mcts.py
litrl/algo/mcts/mcts_config.py
litrl/algo/mcts/node.py
litrl/algo/mcts/recommend.py
litrl/algo/mcts/rollout.py
litrl/algo/mcts/select.py
litrl/algo/mcts/typing.py
litrl/algo/mcts/value.py
litrl/common/__init__.py
litrl/common/agent.py
litrl/common/constants.py
litrl/common/dummy_loader.py
litrl/common/huggingface.py
litrl/common/hydra.py
litrl/common/logger.py
litrl/common/mlflow.py
litrl/common/observation.py
litrl/env/__init__.py
litrl/env/connect_four.py
litrl/env/make.py
litrl/env/type_vars.py
litrl/env/typing.py
litrl/model/__init__.py
litrl/model/base_module.py
litrl/model/sac/__init__.py
litrl/model/sac/model.py
litrl/model/sac/multi_agent.py
litrl/model/sac/multiagent.py
litrl/schema/__init__.py
litrl/schema/agent.py
litrl/schema/callback.py
litrl/schema/config.py
litrl/schema/env.py
litrl/schema/instantiator.py
litrl/schema/logger.py
litrl/schema/model.py
litrl/schema/trainer.py
litrl/type_vars/__init__.py
litrl/type_vars/config.py
litrl/wrappers/__init__.py
litrl/wrappers/clip_reward.py
litrl/wrappers/static_opponent_wrapper.py
litrl/wrappers/validation_wrapper.py
litrl-0.0.24.dist-info/METADATA
litrl-0.0.24.dist-info/WHEEL
litrl-0.0.24.dist-info/top_level.txt
litrl-0.0.24.dist-info/RECORD
