Metadata-Version: 2.1
Name: litrl
Version: 0.0.24
Summary: Implementation of RL algorithms in PyTorch Lightning
Author: Clement Gohlke
Project-URL: Homepage, https://github.com/c-gohlke/LightningRL
Project-URL: Documentation, https://litrl.readthedocs.io/en/latest/
Project-URL: Repository, https://github.com/c-gohlke/LightningRL
Project-URL: Demo, https://huggingface.co/spaces/c-gohlke/litrl-demo
Keywords: pytorch,reinforcement-learning,machine-learning,mypy,pytorch-lightning,huggingface,torchrl
Classifier: Programming Language :: Python :: 3 :: Only
Classifier: Programming Language :: Python :: 3.8
Classifier: Programming Language :: Python :: 3.9
Classifier: Programming Language :: Python :: 3.10
Classifier: Programming Language :: Python :: 3.11
Classifier: License :: OSI Approved :: MIT License
Classifier: Operating System :: OS Independent
Classifier: Intended Audience :: Developers
Classifier: Intended Audience :: Science/Research
Classifier: Topic :: Scientific/Engineering :: Artificial Intelligence
Classifier: Topic :: Software Development :: Libraries :: Python Modules
Classifier: Topic :: Software Development :: Libraries
Classifier: Topic :: Software Development
Classifier: Topic :: Scientific/Engineering
Classifier: Typing :: Typed
Requires-Python: >=3.8
Requires-Dist: swig ==4.1.1
Requires-Dist: Pillow ==10.2.0
Requires-Dist: lightning ==2.1.2
Requires-Dist: hydra-core ==1.3.2
Requires-Dist: nptyping ==2.5.0
Requires-Dist: gymnasium[box2d] ==0.29.1
Requires-Dist: loguru ==0.7.2
Requires-Dist: pettingzoo ==1.24.2
Requires-Dist: pygame ==2.5.2
Requires-Dist: python-dateutil ==2.8.2
Requires-Dist: onnxruntime ==1.16.3
Requires-Dist: scipy ==1.10.1
Requires-Dist: huggingface-hub ==0.19.4
Requires-Dist: mlflow ==2.9.2
Requires-Dist: stable-baselines3 ==2.2.1
Requires-Dist: pydantic ==2.5.2
Requires-Dist: moviepy ==1.0.3
Requires-Dist: onnx ==1.15.0
Requires-Dist: pyrootutils ==1.0.4
Requires-Dist: torchsnapshot ==0.1.0
Provides-Extra: build
Requires-Dist: build ==1.0.3 ; extra == 'build'
Requires-Dist: twine ==4.0.2 ; extra == 'build'
Provides-Extra: demo
Requires-Dist: fastapi ==0.104.1 ; extra == 'demo'
Requires-Dist: uvicorn ==0.25.0 ; extra == 'demo'
Requires-Dist: httpx ==0.26.0 ; extra == 'demo'
Requires-Dist: moviepy ==1.0.3 ; extra == 'demo'
Provides-Extra: dev
Requires-Dist: commitizen ==3.13.0 ; extra == 'dev'
Requires-Dist: litrl[build,doc,lint,test] ; extra == 'dev'
Requires-Dist: nbconvert ==7.14.2 ; extra == 'dev'
Provides-Extra: doc
Requires-Dist: sphinx ==7.1.2 ; extra == 'doc'
Requires-Dist: sphinx-rtd-theme ==2.0.0 ; extra == 'doc'
Requires-Dist: myst-parser ==2.0.0 ; extra == 'doc'
Provides-Extra: lint
Requires-Dist: mypy ==1.7.1 ; extra == 'lint'
Requires-Dist: ruff ==0.1.7 ; extra == 'lint'
Requires-Dist: black ==23.11.0 ; extra == 'lint'
Requires-Dist: vulture ==2.11 ; extra == 'lint'
Requires-Dist: pylint ==3.0.2 ; extra == 'lint'
Requires-Dist: types-python-dateutil ==2.8.19.20240106 ; extra == 'lint'
Requires-Dist: types-PyYAML ==6.0.12.12 ; extra == 'lint'
Requires-Dist: types-requests ==2.31.0.20240106 ; extra == 'lint'
Requires-Dist: bandit ==1.7.7 ; extra == 'lint'
Provides-Extra: test
Requires-Dist: pytest ==7.4.3 ; extra == 'test'
Requires-Dist: types-python-dateutil ==2.8.19.20240106 ; extra == 'test'
Requires-Dist: types-PyYAML ==6.0.12.12 ; extra == 'test'
Requires-Dist: types-requests ==2.31.0.20240106 ; extra == 'test'
Requires-Dist: pytest-cov ==4.1.0 ; extra == 'test'
Requires-Dist: vulture ==2.11 ; extra == 'test'
Requires-Dist: pytest-html ==4.1.1 ; extra == 'test'
Requires-Dist: nbmake ==1.4.6 ; extra == 'test'
Requires-Dist: litrl[demo] ; extra == 'test'
Provides-Extra: torchrl
Requires-Dist: torchrl ==0.2.1 ; extra == 'torchrl'
Requires-Dist: tensordict ==0.2.1 ; extra == 'torchrl'
